django_webhook_receiver/__init__.py
django_webhook_receiver/admin.py
django_webhook_receiver/apps.py
django_webhook_receiver/authentication.py
django_webhook_receiver/models.py
django_webhook_receiver/permissions.py
django_webhook_receiver/management/__init__.py
django_webhook_receiver/management/commands/__init__.py
django_webhook_receiver/migrations/0001_initial.py
django_webhook_receiver/migrations/__init__.py
django_webhook_receiver/tests/__init__.py
django_webhook_receiver/tests/factories.py
django_webhook_receiver/tests/settings.py
django_webhook_receiver/tests/test_authentication.py
django_webhook_receiver/tests/test_models.py
django_webhook_receiver/tests/test_permissions.py
django_webhook_receiver/tests/urls.py
django_webhook_receiver-1.0.0.dist-info/licenses/LICENSE
django_webhook_receiver-1.0.0.dist-info/METADATA
django_webhook_receiver-1.0.0.dist-info/WHEEL
django_webhook_receiver-1.0.0.dist-info/top_level.txt
django_webhook_receiver-1.0.0.dist-info/RECORD
